cortosis/__init__.py
cortosis/metadata.py
cortosis-0.0.0.dist-info/LICENSE
cortosis-0.0.0.dist-info/METADATA
cortosis-0.0.0.dist-info/WHEEL
cortosis-0.0.0.dist-info/top_level.txt
cortosis-0.0.0.dist-info/RECORD
