Metadata-Version: 2.2
Name: cortosis
Version: 0.0.0
Summary: Simple API / WEB and Minion / Daemon frameword
Home-page: https://github.com/interstellio/cortosis
Author: Interstellio IO (PTY) LTD
Author-email: "Interstellio IO (PTY) LTD" <opensource@interstellio.io>
Maintainer: Interstellio IO (PTY) LTD
Maintainer-email: opensource@interstellio.io
License: Apache 2.0
Project-URL: Homepage, https://github.com/interstellio/cortosis
Project-URL: Documentation, https://cortosis.readthedocs.io
Requires-Python: >=3.10
License-File: LICENSE
Dynamic: author
Dynamic: home-page
Dynamic: maintainer
Dynamic: maintainer-email
Dynamic: requires-python
